example_package_joaopcnogueira/__init__.py
example_package_joaopcnogueira/__main__.py
example_package_joaopcnogueira/example.py
example_package_joaopcnogueira-0.1.4.dist-info/METADATA
example_package_joaopcnogueira-0.1.4.dist-info/WHEEL
example_package_joaopcnogueira-0.1.4.dist-info/entry_points.txt
example_package_joaopcnogueira-0.1.4.dist-info/RECORD
