Metadata-Version: 2.1
Name: example_package_joaopcnogueira
Version: 0.1.4
Summary: A small example package
Project-URL: Homepage, https://github.com/joaopcnogueira/packaging_tutorial
Author-email: João Nogueira <joaopcnogueira@gmail.com>, Denise Vitoriano <denisevitoriano@gmail.com>
License-Expression: MIT
Classifier: License :: OSI Approved :: MIT License
Classifier: Operating System :: OS Independent
Classifier: Programming Language :: Python :: 3
Requires-Python: >=3.7
Requires-Dist: numpy
Requires-Dist: pandas
Provides-Extra: dev
Requires-Dist: build; extra == 'dev'
Requires-Dist: pytest; extra == 'dev'
Requires-Dist: twine; extra == 'dev'
